{
  "usuarios": [
    {
      "nombreUsuario": "Enzo",
      "apellido": "Heredia",
      "email": "enzo@gmail.com",
      "contrasena": "123456789",
      "id": 8
    },
    {
      "nombreUsuario": "Santiago",
      "email": "santi@gmail.com",
      "contrasena": "Santi1234gfdg",
      "apellido": "Gonzalez",
      "id": 9
    },
    {
      "nombreUsuario": "Leandro",
      "apellido": "Gonzalez",
      "email": "leandrito@gmail.com",
      "contrasena": "Leandrio1234",
      "id": 10
    },
    {
      "nombreUsuario": "Kike",
      "apellido": "Heredia",
      "email": "kiketuch@gmail.com",
      "contrasena": "1234Aidjfk",
      "id": 11
    },
    {
      "nombreUsuario": "Enzo Alejandro",
      "apellido": "Heredia",
      "email": "eaheredia292@gmail.com",
      "contrasena": "Enzo1235",
      "id": 12
    }
  ]
}